netbox_quicklinks/__about__.py
netbox_quicklinks/__init__.py
netbox_quicklinks/config.py
netbox_quicklinks/urls.py
netbox_quicklinks/views.py
netbox_quicklinks-0.1.1.dist-info/LICENSE.md
netbox_quicklinks-0.1.1.dist-info/METADATA
netbox_quicklinks-0.1.1.dist-info/WHEEL
netbox_quicklinks-0.1.1.dist-info/RECORD
