Metadata-Version: 2.1
Name: netbox-quicklinks
Version: 0.1.1
Summary: Netbox plugin for supporting quick links based on unique item values
Home-page: https://github.com/enpaul/netbox-quicklinks/
License: MIT
Keywords: netbox,plugin,quick,links
Author: Ethan Paul
Author-email: 24588726+enpaul@users.noreply.github.com
Requires-Python: >=3.10,<4.0
Classifier: Development Status :: 4 - Beta
Classifier: Environment :: Plugins
Classifier: Intended Audience :: Developers
Classifier: Intended Audience :: Information Technology
Classifier: Intended Audience :: System Administrators
Classifier: License :: OSI Approved :: MIT License
Classifier: Natural Language :: English
Classifier: Operating System :: OS Independent
Classifier: Programming Language :: Python :: 3
Classifier: Programming Language :: Python :: 3.10
Classifier: Programming Language :: Python :: 3.11
Project-URL: Repository, https://github.com/enpaul/netbox-quicklinks/
